idf2yaml/__init__.py
idf2yaml/__main__.py
idf2yaml/core.py
idf2yaml-0.1.1.dist-info/licenses/LICENSE
idf2yaml-0.1.1.dist-info/METADATA
idf2yaml-0.1.1.dist-info/WHEEL
idf2yaml-0.1.1.dist-info/top_level.txt
idf2yaml-0.1.1.dist-info/RECORD
