Metadata-Version: 2.4
Name: idf2yaml
Version: 0.1.1
Summary: A package for conversion of EnergyPlus IDF files to YAML format (with useful annotation), and back.
Home-page: https://github.com/supsi-dacd-isaac/idf2yaml
Author: Federico Rosato
Author-email: federico.rosato@supsi.ch
License: MIT
Classifier: Programming Language :: Python :: 3
Classifier: Programming Language :: Python :: 3.7
Classifier: Programming Language :: Python :: 3.8
Classifier: Programming Language :: Python :: 3.9
Classifier: Programming Language :: Python :: 3.10
Classifier: Programming Language :: Python :: 3.11
Classifier: License :: OSI Approved :: MIT License
Classifier: Operating System :: OS Independent
Classifier: Development Status :: 4 - Beta
Classifier: Intended Audience :: Science/Research
Classifier: Topic :: Scientific/Engineering
Requires-Python: >=3.7
License-File: LICENSE
Requires-Dist: eppy<1.0.0,>=0.5.60
Requires-Dist: ruamel.yaml<0.18.0,>=0.17.0
Provides-Extra: test
Requires-Dist: numpy<2.0.0,>=1.21.0; extra == "test"
Requires-Dist: pytest<8.0.0,>=7.0.0; extra == "test"
Requires-Dist: pytest-cov<4.0.0,>=3.0.0; extra == "test"
Provides-Extra: dev
Requires-Dist: black<23.0.0,>=22.0.0; extra == "dev"
Requires-Dist: flake8<5.0.0,>=4.0.0; extra == "dev"
Requires-Dist: isort<6.0.0,>=5.0.0; extra == "dev"
Requires-Dist: pre-commit<3.0.0,>=2.0.0; extra == "dev"
Dynamic: license-file
